["[{\"Scores\":{\"type\":\"Integer\",\"value\":2,\"valueInfo\":{}},\"risk category\":{\"type\":\"String\",\"value\":\"Severe Risk\",\"valueInfo\":{}}}]","[{\"score\":{\"type\":\"Integer\",\"value\":5,\"valueInfo\":{}},\"risk category\":{\"type\":\"String\",\"value\":\"healthy kidney function\",\"valueInfo\":{}}}]","[{\"score\":{\"type\":\"Integer\",\"value\":3,\"valueInfo\":{}},\"risk category\":{\"type\":\"String\",\"value\":\"high sodium level\",\"valueInfo\":{}}},{\"score\":{\"type\":\"Integer\",\"value\":5,\"valueInfo\":{}},\"risk category\":{\"type\":\"String\",\"value\":\"normal potassium range\",\"valueInfo\":{}}}]"]